intel_sgx_ra-2.3.3.dist-info/METADATA
intel_sgx_ra-2.3.3.dist-info/WHEEL
intel_sgx_ra-2.3.3.dist-info/entry_points.txt
intel_sgx_ra/maa/__init__.py
intel_sgx_ra/maa/attest.py
intel_sgx_ra/error.py
intel_sgx_ra/globs.py
intel_sgx_ra/ratls.py
intel_sgx_ra/log.py
intel_sgx_ra/quote.py
intel_sgx_ra/base64url.py
intel_sgx_ra/__init__.py
intel_sgx_ra/cli/__init__.py
intel_sgx_ra/cli/utils.py
intel_sgx_ra/cli/verify.py
intel_sgx_ra/py.typed
intel_sgx_ra/lib_sgx_dcap_ratls.pyi
intel_sgx_ra/pccs.py
intel_sgx_ra/attest.py
intel_sgx_ra/signer.py
intel_sgx_ra/pck.py
intel_sgx_ra/lib_sgx_dcap_ratls.cpython-38-darwin.so
intel_sgx_ra-2.3.3.dist-info/RECORD
