Metadata-Version: 2.3
Name: intel-sgx-ra
Version: 2.3.3
Classifier: Programming Language :: Rust
Classifier: Programming Language :: Python :: 3
Classifier: Programming Language :: Python :: Implementation :: CPython
Classifier: License :: OSI Approved :: MIT License
Classifier: Operating System :: OS Independent
Requires-Dist: requests >=2.32.3, <3.0.0
Requires-Dist: cryptography >=43.0.3, <44.0.0
Requires-Dist: authlib >=1.3.2, <2.0.0
Requires-Dist: black >=24.3.0, <25.0.0 ; extra == 'dev'
Requires-Dist: isort >=5.13.2, <6.0.0 ; extra == 'dev'
Requires-Dist: pylint >=3.2.7, <4.0.0 ; extra == 'dev'
Requires-Dist: pycodestyle >=2.12.1, <3.0.0 ; extra == 'dev'
Requires-Dist: pydocstyle >=6.3.0, <7.0.0 ; extra == 'dev'
Requires-Dist: mypy >=1.13.0, <2.0.0 ; extra == 'dev'
Requires-Dist: pytest >=8.3.3, <9.0.0 ; extra == 'dev'
Requires-Dist: types-requests >=2.31.0, <3.0.0 ; extra == 'dev'
Provides-Extra: dev
Summary: Intel SGX Remote Attestation verification library
Author-email: Cosmian Tech <tech@cosmian.com>
License: MIT
Requires-Python: >=3.8
